.gitignore
MANIFEST.in
README.md
setup.py
src/ruddocom/__init__.py
src/ruddocom.pdfiframer.egg-info/PKG-INFO
src/ruddocom.pdfiframer.egg-info/SOURCES.txt
src/ruddocom.pdfiframer.egg-info/dependency_links.txt
src/ruddocom.pdfiframer.egg-info/entry_points.txt
src/ruddocom.pdfiframer.egg-info/namespace_packages.txt
src/ruddocom.pdfiframer.egg-info/not-zip-safe
src/ruddocom.pdfiframer.egg-info/requires.txt
src/ruddocom.pdfiframer.egg-info/top_level.txt
src/ruddocom/pdfiframer/__init__.py
src/ruddocom/pdfiframer/configure.zcml
src/ruddocom/pdfiframer/setuphandlers.py
src/ruddocom/pdfiframer/view.pt
src/ruddocom/pdfiframer/js/download-pdf-icon.svg
src/ruddocom/pdfiframer/js/iframehandling-compiled.js
src/ruddocom/pdfiframer/profiles/default/metadata.xml
src/ruddocom/pdfiframer/profiles/default/registry/iframehandling.xml
src/ruddocom/pdfiframer/profiles/uninstall/metadata.xml
src/ruddocom/pdfiframer/profiles/uninstall/registry/iframehandling.xml