Metadata-Version: 2.1
Name: ruddocom.pdfiframer
Version: 1.1
Summary: PDF IFRAME add-on for Plone
Home-page: https://github.com/Rudd-O/ruddocom.pdfiframer
Author: Manuel Amador (Rudd-O)
Author-email: rudd-o+plone@rudd-o.com
License: GPL version 2 or later
Project-URL: PyPI, https://pypi.python.org/pypi/ruddocom.pdfiframer
Project-URL: Source, https://github.com/Rudd-O/ruddocom.pdfiframer
Project-URL: Tracker, https://github.com/Rudd-O/ruddocom.pdfiframer/issues
Keywords: Python Plone CMS
Platform: UNKNOWN
Classifier: Environment :: Web Environment
Classifier: Framework :: Plone
Classifier: Framework :: Plone :: Addon
Classifier: Framework :: Plone :: 6.0
Classifier: Programming Language :: Python
Classifier: Programming Language :: Python :: 3.6
Classifier: Operating System :: OS Independent
Classifier: License :: OSI Approved :: GNU General Public License v2 or later (GPLv2+)
Requires-Python: >=3.6
Provides-Extra: test
